InfoFuzzyNetwork/IFN.py
InfoFuzzyNetwork/__init__.py
InfoFuzzyNetwork-1.0.4.dist-info/LICENSE
InfoFuzzyNetwork-1.0.4.dist-info/METADATA
InfoFuzzyNetwork-1.0.4.dist-info/WHEEL
InfoFuzzyNetwork-1.0.4.dist-info/top_level.txt
InfoFuzzyNetwork-1.0.4.dist-info/RECORD
