Metadata-Version: 2.1
Name: InfoFuzzyNetwork
Version: 1.0.4
Summary: Implementation of the IFN (Info Fuzzy Network) model for predictions and feature selection on structured data.
Home-page: https://github.com/shaharoded/IFN-Info-Fuzzy-Network
Author: Shahar Oded
Author-email: shahar6771@gmail.com
License: MIT
Classifier: Development Status :: 4 - Beta
Classifier: Programming Language :: Python :: 3
Classifier: Programming Language :: Python :: 3.7
Classifier: Programming Language :: Python :: 3.8
Classifier: Programming Language :: Python :: 3.9
Classifier: Programming Language :: Python :: 3.10
Classifier: License :: OSI Approved :: MIT License
Classifier: Operating System :: OS Independent
Classifier: Intended Audience :: Developers
Classifier: Intended Audience :: Science/Research
Classifier: Topic :: Scientific/Engineering :: Information Analysis
Classifier: Topic :: Scientific/Engineering :: Artificial Intelligence
Requires-Python: >=3.6
License-File: LICENSE
Requires-Dist: numpy
Requires-Dist: pandas
Requires-Dist: scipy
Requires-Dist: networkx
Requires-Dist: matplotlib
Requires-Dist: scikit-learn
